README.md
pyproject.toml
setup.cfg
setup.py
do_sdk_files/__init__.py
do_sdk_files/api_client.py
do_sdk_files/api_response.py
do_sdk_files/configuration.py
do_sdk_files/exceptions.py
do_sdk_files/py.typed
do_sdk_files/rest.py
do_sdk_files.egg-info/PKG-INFO
do_sdk_files.egg-info/SOURCES.txt
do_sdk_files.egg-info/dependency_links.txt
do_sdk_files.egg-info/requires.txt
do_sdk_files.egg-info/top_level.txt
do_sdk_files/api/__init__.py
do_sdk_files/api/do_data_api.py
do_sdk_files/api/files_api.py
do_sdk_files/api/shared_data_api.py
do_sdk_files/models/__init__.py
do_sdk_files/models/file_controller_get_signed_url_download200_response.py
do_sdk_files/models/file_controller_get_signed_url_upload200_response.py
do_sdk_files/models/file_controller_put_object200_response.py
do_sdk_files/models/file_controller_put_object200_response_s3.py
do_sdk_files/models/shared_data_controller_get_do_object200_response.py
do_sdk_files/models/shared_data_controller_get_do_object200_response_one_of.py
test/test_do_data_api.py
test/test_file_controller_get_signed_url_download200_response.py
test/test_file_controller_get_signed_url_upload200_response.py
test/test_file_controller_put_object200_response.py
test/test_file_controller_put_object200_response_s3.py
test/test_files_api.py
test/test_shared_data_api.py
test/test_shared_data_controller_get_do_object200_response.py
test/test_shared_data_controller_get_do_object200_response_one_of.py